migrations/0001_initial.py
migrations/__init__.py
pongjun_note-0.1.2.dist-info/METADATA
pongjun_note-0.1.2.dist-info/WHEEL
pongjun_note-0.1.2.dist-info/top_level.txt
pongjun_note-0.1.2.dist-info/RECORD
