Metadata-Version: 2.1
Name: pongjun-note
Version: 0.1.2
Summary: A reusable Django app for managing notes.
Home-page: https://github.com/i2x/notes
Author: Pongjun
Author-email: s6601012610067@kmutnb.ac.th
License: MIT
Classifier: Environment :: Web Environment
Classifier: Framework :: Django
Classifier: Framework :: Django :: 4.0
Classifier: Intended Audience :: Developers
Classifier: License :: OSI Approved :: MIT License
Classifier: Operating System :: OS Independent
Classifier: Programming Language :: Python
Classifier: Programming Language :: Python :: 3.9
Requires-Dist: Django >=4.0
